hdiutils/__init__.py
hdiutils/HDIexport/__init__.py
hdiutils/HDIexport/hdi_exporter.py
hdiutils/HDIimport/__init__.py
hdiutils/HDIimport/cyt_reader.py
hdiutils/HDIimport/h5_reader.py
hdiutils/HDIimport/hdi_reader.py
hdiutils/HDIimport/imzml_reader.py
hdiutils/HDIimport/nifti1_reader.py
hdiutils/HDIimport/tif_reader.py
hdiutils/HDIimport/utils.py
hdi_utils-0.0.3.1.dist-info/LICENSE
hdi_utils-0.0.3.1.dist-info/METADATA
hdi_utils-0.0.3.1.dist-info/WHEEL
hdi_utils-0.0.3.1.dist-info/top_level.txt
hdi_utils-0.0.3.1.dist-info/RECORD
