Metadata-Version: 2.1
Name: hdi-utils
Version: 0.0.3.1
Summary: High-dimensional image data utilities
Home-page: https://github.com/JoshuaHess12/hdi-utils
Maintainer: Joshua Hess
Maintainer-email: joshmhess12@gmail.com
License: MIT
Keywords: high-dimensional image imaging mulitplex
Platform: UNKNOWN
Classifier: Intended Audience :: Science/Research
Classifier: Intended Audience :: Developers
Classifier: License :: OSI Approved
Classifier: Programming Language :: Python
Classifier: Topic :: Software Development
Classifier: Topic :: Scientific/Engineering
Classifier: Operating System :: Microsoft :: Windows
Classifier: Operating System :: POSIX
Classifier: Operating System :: Unix
Classifier: Operating System :: MacOS
Classifier: Programming Language :: Python :: 3.6
Classifier: Programming Language :: Python :: 3.7
Classifier: Programming Language :: Python :: 3.8
Classifier: Programming Language :: Python :: 3.9
Requires-Dist: numpy (>=1.19.5)
Requires-Dist: pandas (>=1.1.5)
Requires-Dist: pyimzML (>=1.4.1)
Requires-Dist: nibabel (>=3.2.1)
Requires-Dist: h5py (>=3.1.0)
Requires-Dist: scikit-image (>=0.17.2)
Requires-Dist: scipy (>=1.5.4)
